lazydep/__init__.py
lazydep-1.1.dist-info/METADATA
lazydep-1.1.dist-info/WHEEL
lazydep-1.1.dist-info/top_level.txt
lazydep-1.1.dist-info/RECORD
